{
  "build": {
    "content": [
      {
        "files": [
          "api/**.yml",
          "api/index.md"
        ]
      },
      {
        "files": [
          "toc.yml",
          "*.md"
        ]
      }
    ],
    "dest": "../site",
    "globalMetadata": {
      "_appName": "arinc424.net",
      "_appTitle": "arinc424.net"
    },
    "sitemap": {
      "baseUrl": "https://maltraem.github.io/arinc424.net",
      "changefreq": "weekly"
    },
    "template": [
      "default",
      "modern",
      "custom"
    ]
  },
  "metadata": [
    {
      "filter": "filter.yml",
      "dest": "api/",
      "enumSortOrder": "declaringOrder",
      "namespaceLayout": "nested",
      "noRestore": true,
      "src": [
        {
          "files": [
            "source/library/Arinc424.csproj"
          ],
          "src": "../"
        }
      ]
    }
  ]
}
